my_own_package/__init__.py
Lavinia_Mihalache_own_package-0.1.0.dist-info/METADATA
Lavinia_Mihalache_own_package-0.1.0.dist-info/WHEEL
Lavinia_Mihalache_own_package-0.1.0.dist-info/top_level.txt
Lavinia_Mihalache_own_package-0.1.0.dist-info/RECORD
