Metadata-Version: 2.1
Name: Lavinia-Mihalache-own-package
Version: 0.1.0
Summary: my_first_package
Author: Lavinia Mihalache
Author-email: mihalache_mihaela_lavinia@yahoo.com
